mojo/runtime/__init__.py
mojo/runtime/activation.py
mojo/runtime/enumerations.py
mojo/runtime/initialize.py
mojo/runtime/integration.py
mojo/runtime/optionoverrides.py
mojo/runtime/paths.py
mojo/runtime/runtimesettings.py
mojo/runtime/runtimevariables.py
mojo/runtime/variablenames.py
mojo_runtime-2.0.2.dist-info/LICENSE.txt
mojo_runtime-2.0.2.dist-info/METADATA
mojo_runtime-2.0.2.dist-info/WHEEL
mojo_runtime-2.0.2.dist-info/RECORD
